{
    "fluentMethods": true,
    "relationships": [],
    "fields": [
        {
            "fieldName": "emailId",
            "fieldType": "String",
            "fieldValidateRules": [
                "maxlength"
            ],
            "fieldValidateRulesMaxlength": 254
        },
        {
            "fieldName": "phoneNumber",
            "fieldType": "Long"
        },
        {
            "fieldName": "mailPerWeek",
            "fieldType": "Integer"
        },
        {
            "fieldName": "numberOfMailsSent",
            "fieldType": "Integer"
        },
        {
            "fieldName": "active",
            "fieldType": "Boolean",
            "fieldValidateRules": [
                "required"
            ]
        }
    ],
    "changelogDate": "20180214101716",
    "entityTableName": "newsletter",
    "dto": "no",
    "pagination": "no",
    "service": "serviceClass",
    "jpaMetamodelFiltering": false
}